gitpy/__init__.py
gitpy/commit.py
gitpy/commitAdd.py
gitpy/pull.py
gitpy/push.py
gitpy-0.0.5.dist-info/LICENSE
gitpy-0.0.5.dist-info/METADATA
gitpy-0.0.5.dist-info/WHEEL
gitpy-0.0.5.dist-info/top_level.txt
gitpy-0.0.5.dist-info/RECORD
