Metadata-Version: 2.1
Name: gitpy
Version: 0.0.5
Summary: A Python wrapper for git
Home-page: https://github.com/filiptronicek/gitpy
Author: Filip Troníček
Author-email: filip@trnck.dev
License: UNKNOWN
Platform: UNKNOWN
Classifier: Programming Language :: Python :: 3
Classifier: License :: OSI Approved :: MIT License
Classifier: Operating System :: OS Independent
Requires-Python: >=3.6
